[
    {
        "id": 1,
        "name": "Câu lạc đá cầu của thầy Minh"
    },
    {
        "id": 2,
        "name": "Câu lạc bộ Thư viện Hội Sinh viên"
    },
    {
        "id": 3,
        "name": "Câu lạc bộ Nghệ thuật"
    },
    {
        "id": 4,
        "name": "Câu lạc bộ nguồn nhân lực HRTech"
    },
    {
        "id": 5,
        "name": "Câu lạc bộ Tiếng Anh"
    },
    {
        "id": 6,
        "name": "Câu lạc bộ Đá Bóng"
    },
    {
        "id": 7,
        "name": "Câu lạc bộ Điện tử và Tự động hóa"
    },
    {
        "id": 8,
        "name": "Câu lạc bộ Thuyết trình"
    },
    {
        "id": 9,
        "name": "Câu lạc bộ Sinh viên vận động hiến máu"
    },
    {
        "id": 10,
        "name": "Câu lạc bộ Robotics"
    },
    {
        "id": 11,
        "name": "Câu lạc bộ Tiếng Nhật"
    },
    {
        "id": 12,
        "name": "Câu lạc bộ Lý luận trẻ"
    },
    {
        "id": 13,
        "name": "Câu lạc bộ Hỗ trợ sinh viên"
    },
    {
        "id": 14,
        "name": "Câu lạc bộ Truyền thông UETLC"
    },
    {
        "id": 15,
        "name": "Câu lạc bộ Nhảy cổ động"
    },
    {
        "id": 16,
        "name": "Câu lạc bộ Cầu Lông"
    },
    {
        "id": 17,
        "name": "Câu lạc bộ Bóng rổ"
    },
    {
        "id": 18,
        "name": "Câu lạc bộ Hàng không Vũ trụ"
    }
]